gcs_jupyter_plugin/__init__.py
gcs_jupyter_plugin/_version.py
gcs_jupyter_plugin/credentials.py
gcs_jupyter_plugin/handlers.py
gcs_jupyter_plugin/urls.py
gcs_jupyter_plugin/commons/constants.py
gcs_jupyter_plugin/controllers/gcs.py
gcs_jupyter_plugin/services/gcs.py
gcs_jupyter_plugin/tests/__init__.py
gcs_jupyter_plugin/tests/test_handlers.py
gcs_jupyter_plugin-0.1.3.data/data/etc/jupyter/jupyter_server_config.d/gcs_jupyter_plugin.json
gcs_jupyter_plugin-0.1.3.data/data/share/jupyter/labextensions/gcs-jupyter-plugin/build_log.json
gcs_jupyter_plugin-0.1.3.data/data/share/jupyter/labextensions/gcs-jupyter-plugin/package.json
gcs_jupyter_plugin-0.1.3.data/data/share/jupyter/labextensions/gcs-jupyter-plugin/schemas/gcs-jupyter-plugin/package.json.orig
gcs_jupyter_plugin-0.1.3.data/data/share/jupyter/labextensions/gcs-jupyter-plugin/schemas/gcs-jupyter-plugin/plugin.json
gcs_jupyter_plugin-0.1.3.data/data/share/jupyter/labextensions/gcs-jupyter-plugin/static/lib_index_js.7f8f91c83b40890b48e6.js
gcs_jupyter_plugin-0.1.3.data/data/share/jupyter/labextensions/gcs-jupyter-plugin/static/lib_index_js.7f8f91c83b40890b48e6.js.map
gcs_jupyter_plugin-0.1.3.data/data/share/jupyter/labextensions/gcs-jupyter-plugin/static/remoteEntry.f9e98b568234db4a324a.js
gcs_jupyter_plugin-0.1.3.data/data/share/jupyter/labextensions/gcs-jupyter-plugin/static/remoteEntry.f9e98b568234db4a324a.js.map
gcs_jupyter_plugin-0.1.3.data/data/share/jupyter/labextensions/gcs-jupyter-plugin/static/style.js
gcs_jupyter_plugin-0.1.3.data/data/share/jupyter/labextensions/gcs-jupyter-plugin/static/style_index_js.1c799ba5df361fee15e6.js
gcs_jupyter_plugin-0.1.3.data/data/share/jupyter/labextensions/gcs-jupyter-plugin/static/style_index_js.1c799ba5df361fee15e6.js.map
gcs_jupyter_plugin-0.1.3.data/data/share/jupyter/labextensions/gcs-jupyter-plugin/static/vendors-node_modules_mime-types_index_js.53abe3371ff48f322d03.js
gcs_jupyter_plugin-0.1.3.dist-info/METADATA
gcs_jupyter_plugin-0.1.3.dist-info/WHEEL
gcs_jupyter_plugin-0.1.3.dist-info/licenses/LICENSE
gcs_jupyter_plugin-0.1.3.dist-info/RECORD
