Metadata-Version: 2.4
Name: gcs_jupyter_plugin
Version: 0.1.3
Summary: A JupyterLab extension.
Project-URL: Homepage, https://github.com/GoogleCloudDataproc/gcs-jupyter-plugin
Project-URL: Bug Tracker, https://github.com/GoogleCloudDataproc/gcs-jupyter-plugin/issues
Project-URL: Repository, https://github.com/GoogleCloudDataproc/gcs-jupyter-plugin.git
Author-email: Google <gcs-plugins@google.com>
License: This file was generated with the generate-license-file npm package!
License-File: LICENSE
Keywords: jupyter,jupyterlab,jupyterlab-extension
Classifier: Framework :: Jupyter
Classifier: Framework :: Jupyter :: JupyterLab
Classifier: Framework :: Jupyter :: JupyterLab :: 4
Classifier: Framework :: Jupyter :: JupyterLab :: Extensions
Classifier: Framework :: Jupyter :: JupyterLab :: Extensions :: Prebuilt
Classifier: License :: OSI Approved :: BSD License
Classifier: Programming Language :: Python
Classifier: Programming Language :: Python :: 3
Classifier: Programming Language :: Python :: 3.9
Classifier: Programming Language :: Python :: 3.10
Classifier: Programming Language :: Python :: 3.11
Classifier: Programming Language :: Python :: 3.12
Classifier: Programming Language :: Python :: 3.13
Requires-Python: >=3.9
Requires-Dist: aiohttp~=3.9.5
Requires-Dist: google-cloud-jupyter-config>=0.0.10
Requires-Dist: google-cloud-storage~=2.18.2
Requires-Dist: jupyter-server<3,>=2.4.0
Provides-Extra: test
Requires-Dist: coverage; extra == 'test'
Requires-Dist: pytest; extra == 'test'
Requires-Dist: pytest-asyncio; extra == 'test'
Requires-Dist: pytest-cov; extra == 'test'
Requires-Dist: pytest-jupyter[server]>=0.6.0; extra == 'test'
